code_wake_sql14_store/__init__.py
code_wake_sql14_store/pkg_meta.py
code_wake_sql14_store/sql14store.py
code_wake_sql14_store/utils.py
code_wake_sql14_store-0.3.0.dist-info/LICENSE
code_wake_sql14_store-0.3.0.dist-info/METADATA
code_wake_sql14_store-0.3.0.dist-info/WHEEL
code_wake_sql14_store-0.3.0.dist-info/entry_points.txt
code_wake_sql14_store-0.3.0.dist-info/top_level.txt
code_wake_sql14_store-0.3.0.dist-info/RECORD
